Metadata-Version: 2.4
Name: adafruit-circuitpython-servokit
Version: 1.3.20
Summary: CircuitPython helper library for PWM/Servo FeatherWing, Shield, and Pi HAT and Bonnet kits.
Author-email: Adafruit Industries <circuitpython@adafruit.com>
License: MIT
Project-URL: Homepage, https://github.com/adafruit/Adafruit_CircuitPython_ServoKit
Keywords: adafruit,servo,motor,pwm,pca9685,featherwing,pi,shield,bonnet,servokit,kit,i2c,hardware,micropython,circuitpython
Classifier: Intended Audience :: Developers
Classifier: Topic :: Software Development :: Libraries
Classifier: Topic :: Software Development :: Embedded Systems
Classifier: Topic :: System :: Hardware
Classifier: License :: OSI Approved :: MIT License
Classifier: Programming Language :: Python :: 3
License-File: LICENSE
Requires-Dist: Adafruit-Blinka>=7.0.0
Requires-Dist: adafruit-circuitpython-busdevice
Requires-Dist: adafruit-circuitpython-pca9685
Requires-Dist: adafruit-circuitpython-motor
Requires-Dist: adafruit-circuitpython-register
Provides-Extra: optional
Dynamic: license-file
